deteksigempa/__init__.py
gempaterkini_indonesia-0.1.dist-info/LICENSE
gempaterkini_indonesia-0.1.dist-info/METADATA
gempaterkini_indonesia-0.1.dist-info/WHEEL
gempaterkini_indonesia-0.1.dist-info/top_level.txt
gempaterkini_indonesia-0.1.dist-info/RECORD
