Metadata-Version: 2.1
Name: gempaterkini-indonesia
Version: 0.1
Summary: This package will get the latest earthquake from BMKG
Home-page: https://github.com/teolloDEV/Indonesia-last-earthquake
Author: Nur Arif
Author-email: nurarif0151@gmail.com
License: The Unlicense
Project-URL: Website, https://nurarif.com
Classifier: Programming Language :: Python :: 3
Classifier: License :: OSI Approved :: GNU General Public License v3 (GPLv3)
Classifier: Operating System :: OS Independent
Classifier: Development Status :: 5 - Production/Stable
Requires-Python: >=3.8
License-File: LICENSE
